setup.py
recaptcha/__init__.py
recaptcha/verifier.py
recaptcha_wrapper.egg-info/PKG-INFO
recaptcha_wrapper.egg-info/SOURCES.txt
recaptcha_wrapper.egg-info/dependency_links.txt
recaptcha_wrapper.egg-info/top_level.txt