Metadata-Version: 1.0
Name: recaptcha-wrapper
Version: 0.1
Summary: Wrapper for Google reCAPTCHA
Home-page: https://github.com/JunePlum/reCAPTCHA-Wrapper
Author: Javon Davis
Author-email: javonldavis14@gmail.com, howarde.jr@hotmail.com, alexj.nich@hotmail.com
License: MIT
Platform: UNKNOWN
